tsdataloader-0.1.0.dist-info/METADATA
tsdataloader-0.1.0.dist-info/WHEEL
tsdataloader-0.1.0.dist-info/entry_points.txt
tsdataloader/__init__.py
tsdataloader/dataloader.py
tsdataloader/dataset.py
tsdataloader/logging_config.py
tsdataloader-0.1.0.dist-info/RECORD
