Metadata-Version: 2.1
Name: tsdataloader
Version: 0.1.0
Summary: From database(PostgreSQL, ...) to PyTorch Dataloader.
Author-Email: Taeyong Jeon <taeyongjeon24@gmail.com>
License: MIT
Project-URL: Repository, https://github.com/tyjeon24/tsdataloader
Requires-Python: >=3.10
Requires-Dist: psycopg2-binary>=2.9.10
Requires-Dist: torch>=2.5.1
